cylc/rose/__init__.py
cylc/rose/entry_points.py
cylc/rose/fileinstall.py
cylc/rose/jinja2_parser.py
cylc/rose/platform_utils.py
cylc/rose/py.typed
cylc/rose/stem.py
cylc/rose/utilities.py
cylc_rose-1.7.0.dist-info/licenses/COPYING
cylc_rose-1.7.0.dist-info/METADATA
cylc_rose-1.7.0.dist-info/WHEEL
cylc_rose-1.7.0.dist-info/entry_points.txt
cylc_rose-1.7.0.dist-info/top_level.txt
cylc_rose-1.7.0.dist-info/RECORD
