Metadata-Version: 2.4
Name: cylc-rose
Version: 1.7.0
Summary: A Cylc plugin providing support for the Rose rose-suite.conf file.
Home-page: https://cylc.github.io/cylc-doc/latest/html/plugins/cylc-rose.html
Author: British Crown (Met Office) & Contributors
Author-email: metomi@metoffice.gov.uk
License: GPL
Keywords: cylc,rose,workflow,configuration,workflow-engine,workflow-automation,workflow-management
Platform: any
Classifier: Environment :: Console
Classifier: Intended Audience :: Developers
Classifier: Intended Audience :: System Administrators
Classifier: Intended Audience :: Science/Research
Classifier: Operating System :: POSIX :: Linux
Classifier: Programming Language :: Python
Classifier: Programming Language :: Python :: 3 :: Only
Classifier: Programming Language :: Python :: Implementation :: CPython
Classifier: Topic :: Scientific/Engineering :: Atmospheric Science
Requires-Python: >=3.12
License-File: COPYING
Requires-Dist: metomi-rose==2.6.*
Requires-Dist: cylc-flow==8.6.*
Requires-Dist: metomi-isodatetime
Requires-Dist: ansimarkup
Requires-Dist: jinja2
Provides-Extra: tests
Requires-Dist: coverage>=5.0.0; extra == "tests"
Requires-Dist: pytest>=6.2.0; extra == "tests"
Requires-Dist: pytest-asyncio==0.21.*; extra == "tests"
Requires-Dist: pytest-cov; extra == "tests"
Requires-Dist: pytest-xdist>=2; extra == "tests"
Requires-Dist: towncrier>=24.7.0; extra == "tests"
Provides-Extra: lint
Requires-Dist: flake8; extra == "lint"
Requires-Dist: flake8-broken-line>=0.3.0; extra == "lint"
Requires-Dist: flake8-bugbear>=21.0.0; extra == "lint"
Requires-Dist: flake8-builtins>=1.5.0; extra == "lint"
Requires-Dist: flake8-comprehensions>=3.5.0; extra == "lint"
Requires-Dist: flake8-debugger>=4.0.0; extra == "lint"
Requires-Dist: flake8-mutable>=1.2.0; extra == "lint"
Requires-Dist: flake8-simplify>=0.15.1; extra == "lint"
Requires-Dist: flake8-type-checking; extra == "lint"
Requires-Dist: mypy>=0.910; extra == "lint"
Provides-Extra: all
Requires-Dist: coverage>=5.0.0; extra == "all"
Requires-Dist: pytest>=6.2.0; extra == "all"
Requires-Dist: pytest-asyncio==0.21.*; extra == "all"
Requires-Dist: pytest-cov; extra == "all"
Requires-Dist: pytest-xdist>=2; extra == "all"
Requires-Dist: towncrier>=24.7.0; extra == "all"
Requires-Dist: flake8; extra == "all"
Requires-Dist: flake8-broken-line>=0.3.0; extra == "all"
Requires-Dist: flake8-bugbear>=21.0.0; extra == "all"
Requires-Dist: flake8-builtins>=1.5.0; extra == "all"
Requires-Dist: flake8-comprehensions>=3.5.0; extra == "all"
Requires-Dist: flake8-debugger>=4.0.0; extra == "all"
Requires-Dist: flake8-mutable>=1.2.0; extra == "all"
Requires-Dist: flake8-simplify>=0.15.1; extra == "all"
Requires-Dist: flake8-type-checking; extra == "all"
Requires-Dist: mypy>=0.910; extra == "all"
Dynamic: license-file
